{
  "name": "forword文字图标库",
  "description": "nori-emby",
  "icons": [
    {
      "name": "Lyrebird",
      "url": "https://raw.githubusercontent.com/nori5555/nori-emby/main/icons/lyrebird.png"
    },
    {
      "name": "Temby",
      "url": "https://raw.githubusercontent.com/nori5555/nori-emby/main/icons/temby.jpg"
    },
    {
      "name": "Moon",
      "url": "https://raw.githubusercontent.com/nori5555/nori-emby/main/icons/moon.png"
    },
    {
      "name": "纸片人",
      "url": "https://raw.githubusercontent.com/nori5555/nori-emby/main/icons/paper.png"
    },
    {
      "name": "见手青",
      "url": "https://raw.githubusercontent.com/nori5555/nori-emby/main/icons/mushroom.png"
    },
    {
      "name": "Nya",
      "url": "https://raw.githubusercontent.com/nori5555/nori-emby/main/icons/nya.png"
    },
    {
      "name": "Charontv",
      "url": "https://raw.githubusercontent.com/nori5555/nori-emby/main/icons/charontv.png"
    }
  ]
}
